hat/orchestrator/ui/script/snabbdom/htmldomapi.d.ts
hat/orchestrator/ui/script/snabbdom/modules/attributes.d.ts
hat/orchestrator/ui/script/snabbdom/tovnode.js
hat/orchestrator/ui/style/main.css
hat/orchestrator/ui/script/snabbdom/h.js.map
hat/orchestrator/ui/script/snabbdom/index.d.ts
hat/orchestrator/ui/script/@hat-open/util/misc.d.ts
hat/orchestrator/ui/script/@hat-open/util/misc.js
hat/orchestrator/ui/script/main.js
hat/orchestrator/ui/script/snabbdom/is.js
hat/orchestrator/ui/script/@hat-open/util/file.d.ts
hat/orchestrator/ui/script/snabbdom/vnode.d.ts
hat/orchestrator/ui/script/@hat-open/juggler/README.md
hat/orchestrator/ui/script/@hat-open/juggler/index.d.ts
hat/orchestrator/ui/icons/LICENSE
hat/orchestrator/ui/script/snabbdom/init.js.map
hat/orchestrator/ui/script/@hat-open/util/dragger.js
hat/orchestrator/ui/script/snabbdom/modules/style.js
hat/orchestrator/ui/script/@hat-open/util/dragger.d.ts
hat/orchestrator/ui/script/@hat-open/util/README.md
hat/orchestrator/ui/script/snabbdom/hooks.js.map
hat/orchestrator/__main__.py
hat/orchestrator/component.py
hat/orchestrator/ui/script/snabbdom/thunk.d.ts
hat/orchestrator/ui/script/snabbdom/init.js
hat/orchestrator/ui/script/snabbdom/modules/class.js
hat/orchestrator/ui/script/@hat-open/juggler/index.js
hat/orchestrator/ui/script/snabbdom/vnode.js.map
hat/orchestrator/ui/script/@hat-open/util/promise.js
hat/orchestrator/ui/script/@hat-open/renderer/README.md
hat/orchestrator/ui.py
hat/orchestrator/ui/script/snabbdom/thunk.js
hat/orchestrator/ui/script/snabbdom/index.js
hat/orchestrator/ui/script/snabbdom/modules/module.js.map
hat/orchestrator/ui/script/snabbdom/modules/attributes.js
hat/orchestrator/process.py
hat/orchestrator/ui/script/snabbdom/modules/dataset.d.ts
hat/orchestrator/ui/index.html
hat/orchestrator/ui/script/@hat-open/util/vnode.d.ts
hat/orchestrator/ui/script/snabbdom/modules/style.d.ts
hat/orchestrator/ui/script/snabbdom/h.d.ts
hat/orchestrator/ui/script/snabbdom/helpers/attachto.js.map
hat_orchestrator-0.7.8.dist-info/LICENSE
hat_orchestrator-0.7.8.dist-info/entry_points.txt
hat_orchestrator-0.7.8.dist-info/METADATA
hat_orchestrator-0.7.8.dist-info/WHEEL
hat_orchestrator-0.7.8.dist-info/RECORD
