Metadata-Version: 2.1
Name: hat-orchestrator
Version: 0.7.8
Summary: Hat orchestrator
License: Apache-2.0
Classifier: Programming Language :: Python :: 3
Classifier: License :: OSI Approved :: Apache Software License
Provides-Extra: dev
Requires-Dist: appdirs ~=1.4.4
Requires-Dist: hat-aio ~=0.7.11
Requires-Dist: hat-json ~=0.6.1
Requires-Dist: hat-juggler ~=0.7.0
Requires-Dist: hat-util ~=0.6.17
Requires-Dist: hat-doit ~=0.16.0; extra == 'dev'
Requires-Dist: psutil >=5.9.5; extra == 'dev'
Requires-Dist: sphinxcontrib-programoutput >=0.17; extra == 'dev'
Requires-Python: >=3.10
Project-URL: Homepage, http://hat-open.com
Project-URL: Repository, https://github.com/hat-open/hat-orchestrator.git
Project-URL: Documentation, http://hat-orchestrator.hat-open.com
